dictIO/__init__.py
dictIO/cpp_dict.py
dictIO/dict.py
dictIO/dict_parser.py
dictIO/dict_reader.py
dictIO/dict_writer.py
dictIO/formatter.py
dictIO/parser.py
dictIO/py.typed
dictIO/types.py
dictIO/cli/__init__.py
dictIO/cli/dict_parser.py
dictIO/utils/__init__.py
dictIO/utils/counter.py
dictIO/utils/dict.py
dictIO/utils/logging.py
dictIO/utils/path.py
dictIO/utils/strings.py
dictio-0.4.2.dist-info/METADATA
dictio-0.4.2.dist-info/WHEEL
dictio-0.4.2.dist-info/entry_points.txt
dictio-0.4.2.dist-info/licenses/LICENSE
dictio-0.4.2.dist-info/RECORD
