Metadata-Version: 2.4
Name: dictIO
Version: 0.4.2
Summary: Python package to read, write and manipulate dictionary text files. Supports dictIOs native file format, as well as JSON, XML and OpenFOAM.
Project-URL: Homepage, https://github.com/dnv-opensource/dictIO
Project-URL: Documentation, https://dnv-opensource.github.io/dictIO/README.html
Project-URL: Repository, https://github.com/dnv-opensource/dictIO.git
Project-URL: Issues, https://github.com/dnv-opensource/dictIO/issues
Project-URL: Changelog, https://github.com/dnv-opensource/dictIO/blob/main/CHANGELOG.md
Author-email: Frank Lumpitzsch <frank.lumpitzsch@dnv.com>, Claas Rostock <claas.rostock@dnv.com>, Seunghyeon Yoo <seunghyeon.yoo@dnv.com>
Maintainer-email: Claas Rostock <claas.rostock@dnv.com>
License: MIT License
License-File: LICENSE
Keywords: dict,dictIO,dictParser
Classifier: Development Status :: 5 - Production/Stable
Classifier: Environment :: Console
Classifier: Intended Audience :: Developers
Classifier: Intended Audience :: Science/Research
Classifier: License :: OSI Approved :: MIT License
Classifier: Operating System :: MacOS
Classifier: Operating System :: Microsoft :: Windows
Classifier: Operating System :: POSIX :: Linux
Classifier: Programming Language :: Python :: 3.11
Classifier: Programming Language :: Python :: 3.12
Classifier: Programming Language :: Python :: 3.13
Classifier: Programming Language :: Python :: 3.14
Classifier: Topic :: Scientific/Engineering
Classifier: Topic :: Software Development :: Libraries :: Python Modules
Requires-Python: <3.15,>=3.11
Requires-Dist: jsonschema>=4.20
Requires-Dist: lxml>=6.0
Requires-Dist: numpy>=2.3
